{
    "username": "Nombre de usuario",
    "password": "Contraseña",
    "login": "Iniciar sesión",
    "details": "Detalles",
    "wrong_password": "La contraseña es incorrecta. Verifique e intente nuevamente",
    "choose_otp": "Seleccione el método OTP",
    "auth_not_valid": "La política de autenticación requiere pasos adicionales: contacte con el administrador para más información",
    "server_not_responding": "El servidor no responde. Contacte con el administrador del mismo",
    "two_step_authentication": "Verificación en dos pasos",
    "type_otp": "Ingresa aquí la contraseña de un solo uso (OTP)",
    "unsupported_version": "El servidor envió una respuesta inválida. Contacte con el administrador del mismo",
    "offline": "Sin conexión. Por favor, compruebe la conexión a Internet",
    "login_saml": "Autenticación SAML",
    "all_rights_reserved": "Todos los derechos reservados",
    "cant_login": "No fue posible iniciar sesión",
    "credentials_not_valid": "Las credenciales no son válidas. Compruebe los datos e intente de nuevo",
    "changePassword_oldPassword": "Contraseña antigua",
    "changePassword_newPassword": "Nueva contraseña",
    "changePassword_error_minLength": "La longitud mínima es de {{num}} caracteres",
    "changePassword_error_maxLength": "La longitud máxima es de {{num}} caracteres",
    "changePassword_confirmNewPassword": "Confirmar nueva contraseña",
    "changePassword_error_confirmPassword": "Las contraseñas no coinciden",
    "trust_device_and_ip": "Confiar en el dispositivo y dirección IP",
    "changePassword_title": "Cambio de contraseña requerido",
    "changePassword_error_passwordRecentlyUsed": "La contraseña ya ha sido utilizada recientemente",
    "changePassword_error_minUppercaseChars": "Se requieren al menos {{num}} caracteres en mayúsculas",
    "changePassword_error_minPunctuationChars": "Se requieren al menos {{num}} signos de puntuación",
    "changePassword_error_minNumericChars": "Se requieren al menos {{num}} caracteres numéricos",
    "changePassword_error_minLowerCaseChars": "Se requieren al menos {{num}} caracteres en minúscula",
    "changePassword_confirm_label": "Actualizar contraseña e ingresar",
    "carbonio_authentication": "Autenticación de Carbonio",
    "server_unreachable": "Error 502: Service Unreachable - Retry later.",
    "changePassword_error_block_personal_data": "Contraseña inválida: la contraseña contiene el nombre de usuario u otros datos personales: {{str}}",
    "code": "Código",
    "submit": "Enviar",
    "are_you_using_a_small_screen?": "¿Estás utilizando una ventana pequeña?"
}
